numpy2tfrecord/__init__.py
numpy2tfrecord/core.py
numpy2tfrecord-0.0.3.dist-info/LICENSE
numpy2tfrecord-0.0.3.dist-info/METADATA
numpy2tfrecord-0.0.3.dist-info/WHEEL
numpy2tfrecord-0.0.3.dist-info/top_level.txt
numpy2tfrecord-0.0.3.dist-info/RECORD
