Metadata-Version: 2.1
Name: numpy2tfrecord
Version: 0.0.3
Summary: Convert a collection of numpy data to tfrecord
Home-page: https://github.com/yonetaniryo/numpy2tfrecord
Author: Ryo Yonetani
Author-email: yonetani.vision@gmail.com
License: MIT License
Keywords: numpy,tfrecord,tensorflow
License-File: LICENSE
Requires-Dist: numpy (>=1.22.0)
Requires-Dist: tensorflow ; platform_system == "Windows"
Requires-Dist: tensorflow-macos ; platform_system == "darwin"
Requires-Dist: tensorflow ; platform_system == "linux"
